request_log
