Metadata-Version: 2.1
Name: request-log-info
Version: 1.0.0
Summary: UNKNOWN
Home-page: https://github.com/zhangruyu/request_log_info
Author: zhangruyu
Author-email: 1582034460@qq.com
License: BSD
Platform: UNKNOWN
Classifier: Programming Language :: Python :: 3
Classifier: License :: OSI Approved :: BSD License
Classifier: Operating System :: OS Independent
